jurity/__init__.py
jurity/_version.py
jurity/constants.py
jurity/utils.py
jurity/utils_hash.py
jurity/utils_proba.py
jurity/classification/__init__.py
jurity/classification/accuracy.py
jurity/classification/auc.py
jurity/classification/base.py
jurity/classification/f1.py
jurity/classification/precision.py
jurity/classification/recall.py
jurity/fairness/__init__.py
jurity/fairness/average_odds.py
jurity/fairness/base.py
jurity/fairness/disparate_impact.py
jurity/fairness/equal_opportunity.py
jurity/fairness/fnr_difference.py
jurity/fairness/for_difference.py
jurity/fairness/generalized_entropy.py
jurity/fairness/predictive_equality.py
jurity/fairness/statistical_parity.py
jurity/fairness/theil_index.py
jurity/mitigation/__init__.py
jurity/mitigation/base.py
jurity/mitigation/equalized_odds.py
jurity/recommenders/__init__.py
jurity/recommenders/auc.py
jurity/recommenders/base.py
jurity/recommenders/combined.py
jurity/recommenders/ctr.py
jurity/recommenders/diversity.py
jurity/recommenders/map.py
jurity/recommenders/ndcg.py
jurity/recommenders/precision.py
jurity/recommenders/recall.py
jurity-2.1.0.dist-info/LICENSE
jurity-2.1.0.dist-info/METADATA
jurity-2.1.0.dist-info/NOTICES
jurity-2.1.0.dist-info/WHEEL
jurity-2.1.0.dist-info/top_level.txt
jurity-2.1.0.dist-info/RECORD
