Metadata-Version: 2.1
Name: jurity
Version: 2.1.0
Summary: fairness and evaluation library
Home-page: https://github.com/fidelity/jurity
Author: FMR LLC
Project-URL: Source, https://github.com/fidelity/jurity
Classifier: License :: OSI Approved :: Apache Software License
Classifier: Programming Language :: Python :: 3.8
Classifier: Operating System :: OS Independent
Requires-Python: >=3.8
License-File: LICENSE
License-File: NOTICES
Requires-Dist: cvxpy >=1.0.7
Requires-Dist: numpy
Requires-Dist: pandas
Requires-Dist: scikit-learn
